{
  "season_averages": [
    {
      "season": "2020&ndash;21",
      "age": "28",
      "team": "GSW",
      "URL": "GSW",
      "games": "57",
      "minutes": "18.9",
      "pts": "6.5",
      "reb": "3.2",
      "ast": "1.3",
      "stl": "0.7",
      "blk": "0.1",
      "pt3m": "1.4",
      "fgpct": "46.7",
      "ftpct": "90.9",
      "to": "0.5",
      "oreb": "0.4",
      "dreb": "2.8",
      "pt3a": "3.4",
      "pt3pct": "39.7",
      "fgm": "2.2",
      "fga": "4.8",
      "ftm": "0.7",
      "fta": "0.8",
      "pt3mtotal": "77",
      "pt3atotal": "194",
      "fgmtotal": "128",
      "fgatotal": "274",
      "ftmtotal": "40",
      "ftatotal": "44"
    },
    {
      "season": "2021&ndash;22",
      "age": "29",
      "team": "GSW",
      "URL": "GSW",
      "games": "63",
      "minutes": "19.9",
      "pts": "7.4",
      "reb": "3.2",
      "ast": "1.0",
      "stl": "0.6",
      "blk": "0.1",
      "pt3m": "1.0",
      "fgpct": "44.1",
      "ftpct": "88.0",
      "to": "0.6",
      "oreb": "0.4",
      "dreb": "2.8",
      "pt3a": "3.0",
      "pt3pct": "33.7",
      "fgm": "2.7",
      "fga": "6.1",
      "ftm": "1.0",
      "fta": "1.2",
      "pt3mtotal": "63",
      "pt3atotal": "187",
      "fgmtotal": "169",
      "fgatotal": "383",
      "ftmtotal": "66",
      "ftatotal": "75"
    },
    {
      "season": "2022&ndash;23",
      "age": "30",
      "team": "PHX",
      "URL": "PHX",
      "games": "74",
      "minutes": "20.4",
      "pts": "8.2",
      "reb": "3.0",
      "ast": "1.3",
      "stl": "0.4",
      "blk": "0.1",
      "pt3m": "1.5",
      "fgpct": "44.2",
      "ftpct": "90.4",
      "to": "1.1",
      "oreb": "0.5",
      "dreb": "2.5",
      "pt3a": "3.3",
      "pt3pct": "44.5",
      "fgm": "2.7",
      "fga": "6.1",
      "ftm": "1.3",
      "fta": "1.4",
      "pt3mtotal": "110",
      "pt3atotal": "247",
      "fgmtotal": "200",
      "fgatotal": "452",
      "ftmtotal": "94",
      "ftatotal": "104"
    },
    {
      "season": "2024&ndash;25",
      "age": "32",
      "team": "PHX",
      "URL": "PHX",
      "games": "8",
      "minutes": "6.0",
      "pts": "2.4",
      "reb": "0.8",
      "ast": "0.6",
      "stl": "0.3",
      "blk": "0.0",
      "pt3m": "0.1",
      "fgpct": "23.8",
      "ftpct": "100.0",
      "to": "0.4",
      "oreb": "0.1",
      "dreb": "0.6",
      "pt3a": "1.5",
      "pt3pct": "8.3",
      "fgm": "0.6",
      "fga": "2.6",
      "ftm": "1.0",
      "fta": "1.0",
      "pt3mtotal": "1",
      "pt3atotal": "12",
      "fgmtotal": "5",
      "fgatotal": "21",
      "ftmtotal": "8",
      "ftatotal": "8"
    }
  ],
  "game_logs": [
    {
      "playerid": "",
      "team": "PHX",
      "date": "Jan 6",
      "fulldate": "",
      "gamedate": "2025-01-06 00:00:00",
      "gameid": "2694586",
      "gametype": "",
      "rotogameid": "",
      "opp": "@PHI",
      "oppraw": "PHI",
      "teamURL": "",
      "home": "",
      "score": "99-<span class=\"bold\">109</span>",
      "gameURL": "/basketball/box-score/76ers-vs-suns-2025-01-06-2694586",
      "min": "DNP",
      "started": "",
      "pts": "",
      "reb": "",
      "ast": "",
      "stl": "",
      "blk": "",
      "to": "",
      "fgm": "",
      "fga": "",
      "ftm": "",
      "fta": "",
      "pt3fgm": "",
      "pt3fga": "",
      "oreb": "",
      "dreb": "",
      "fouls": "",
      "nbafpts": "",
      "fgpct": "",
      "pt3fgpct": "",
      "ftpct": "",
      "playedgame": "",
      "season": "",
      "nbaPts": "",
      "fanduelPts": "",
      "draftkingsPts": "",
      "yahooPts": "",
      "sorarePts": "",
      "fanballPts": "",
      "head2headPts": "",
      "dream11Pts": ""
    },
    {
      "playerid": "3947",
      "team": "PHX",
      "date": "Jan 4",
      "fulldate": "01/04/2025",
      "gamedate": "2025-01-04 00:00:00",
      "gameid": "2694262",
      "gametype": "REGULAR",
      "rotogameid": "43900",
      "opp": "@IND",
      "oppraw": "IND",
      "teamURL": "/basketball/team/indiana-pacers-ind",
      "home": false,
      "score": "126-<span class=\"bold\">108</span>",
      "gameURL": "/basketball/box-score/pacers-vs-suns-2025-01-04-2694262",
      "min": "1",
      "started": "",
      "pts": "2",
      "reb": "1",
      "ast": "0",
      "stl": "0",
      "blk": "0",
      "to": "0",
      "fgm": "0",
      "fga": "0",
      "ftm": "2",
      "fta": "2",
      "pt3fgm": "0",
      "pt3fga": "0",
      "oreb": "1",
      "dreb": "0",
      "fouls": "0",
      "nbafpts": "3.2",
      "fgpct": 0,
      "pt3fgpct": 0,
      "ftpct": 1,
      "playedgame": "1",
      "season": "2024",
      "nbaPts": "3.2",
      "fanduelPts": "3.2",
      "draftkingsPts": "3.3",
      "yahooPts": "3.2",
      "sorarePts": "3.2",
      "fanballPts": "3.3",
      "head2headPts": "0.0",
      "dream11Pts": "3.2"
    },
    {
      "playerid": "3947",
      "team": "PHX",
      "date": "Dec 31",
      "fulldate": "12/31/2024",
      "gamedate": "2024-12-31 00:00:00",
      "gameid": "2694534",
      "gametype": "REGULAR",
      "rotogameid": "43878",
      "opp": "MEM",
      "oppraw": "MEM",
      "teamURL": "/basketball/team/memphis-grizzlies-mem",
      "home": true,
      "score": "<span class=\"bold\">112</span>-117",
      "gameURL": "/basketball/box-score/suns-vs-grizzlies-2024-12-31-2694534",
      "min": "2",
      "started": "",
      "pts": "0",
      "reb": "0",
      "ast": "0",
      "stl": "0",
      "blk": "0",
      "to": "0",
      "fgm": "0",
      "fga": "1",
      "ftm": "0",
      "fta": "0",
      "pt3fgm": "0",
      "pt3fga": "1",
      "oreb": "0",
      "dreb": "0",
      "fouls": "0",
      "nbafpts": ".0",
      "fgpct": 0,
      "pt3fgpct": 0,
      "ftpct": 0,
      "playedgame": "1",
      "season": "2024",
      "nbaPts": "0.0",
      "fanduelPts": "0.0",
      "draftkingsPts": "0.0",
      "yahooPts": "0.0",
      "sorarePts": "0.0",
      "fanballPts": "0.0",
      "head2headPts": "0.0",
      "dream11Pts": "0.0"
    },
    {
      "playerid": "",
      "team": "PHX",
      "date": "Dec 28",
      "fulldate": "",
      "gamedate": "2024-12-28 00:00:00",
      "gameid": "2694100",
      "gametype": "",
      "rotogameid": "",
      "opp": "@GSW",
      "oppraw": "GSW",
      "teamURL": "",
      "home": "",
      "score": "109-<span class=\"bold\">105</span>",
      "gameURL": "/basketball/box-score/warriors-vs-suns-2024-12-28-2694100",
      "min": "DNP",
      "started": "",
      "pts": "",
      "reb": "",
      "ast": "",
      "stl": "",
      "blk": "",
      "to": "",
      "fgm": "",
      "fga": "",
      "ftm": "",
      "fta": "",
      "pt3fgm": "",
      "pt3fga": "",
      "oreb": "",
      "dreb": "",
      "fouls": "",
      "nbafpts": "",
      "fgpct": "",
      "pt3fgpct": "",
      "ftpct": "",
      "playedgame": "",
      "season": "",
      "nbaPts": "",
      "fanduelPts": "",
      "draftkingsPts": "",
      "yahooPts": "",
      "sorarePts": "",
      "fanballPts": "",
      "head2headPts": "",
      "dream11Pts": ""
    },
    {
      "playerid": "3947",
      "team": "PHX",
      "date": "Dec 27",
      "fulldate": "12/27/2024",
      "gamedate": "2024-12-27 00:00:00",
      "gameid": "2694532",
      "gametype": "REGULAR",
      "rotogameid": "43852",
      "opp": "DAL",
      "oppraw": "DAL",
      "teamURL": "/basketball/team/dallas-mavericks-dal",
      "home": true,
      "score": "<span class=\"bold\">89</span>-98",
      "gameURL": "/basketball/box-score/suns-vs-mavericks-2024-12-27-2694532",
      "min": "1",
      "started": "",
      "pts": "2",
      "reb": "0",
      "ast": "0",
      "stl": "0",
      "blk": "0",
      "to": "0",
      "fgm": "1",
      "fga": "2",
      "ftm": "0",
      "fta": "0",
      "pt3fgm": "0",
      "pt3fga": "0",
      "oreb": "0",
      "dreb": "0",
      "fouls": "0",
      "nbafpts": "2.0",
      "fgpct": 0.5,
      "pt3fgpct": 0,
      "ftpct": 0,
      "playedgame": "1",
      "season": "2024",
      "nbaPts": "2.0",
      "fanduelPts": "2.0",
      "draftkingsPts": "2.0",
      "yahooPts": "2.0",
      "sorarePts": "2.0",
      "fanballPts": "2.0",
      "head2headPts": "0.0",
      "dream11Pts": "2.0"
    },
    {
      "playerid": "",
      "team": "PHX",
      "date": "Dec 25",
      "fulldate": "",
      "gamedate": "2024-12-25 00:00:00",
      "gameid": "2694529",
      "gametype": "",
      "rotogameid": "",
      "opp": "DEN",
      "oppraw": "DEN",
      "teamURL": "",
      "home": "",
      "score": "<span class=\"bold\">110</span>-100",
      "gameURL": "/basketball/box-score/suns-vs-nuggets-2024-12-25-2694529",
      "min": "DNP",
      "started": "",
      "pts": "",
      "reb": "",
      "ast": "",
      "stl": "",
      "blk": "",
      "to": "",
      "fgm": "",
      "fga": "",
      "ftm": "",
      "fta": "",
      "pt3fgm": "",
      "pt3fga": "",
      "oreb": "",
      "dreb": "",
      "fouls": "",
      "nbafpts": "",
      "fgpct": "",
      "pt3fgpct": "",
      "ftpct": "",
      "playedgame": "",
      "season": "",
      "nbaPts": "",
      "fanduelPts": "",
      "draftkingsPts": "",
      "yahooPts": "",
      "sorarePts": "",
      "fanballPts": "",
      "head2headPts": "",
      "dream11Pts": ""
    },
    {
      "playerid": "3947",
      "team": "PHX",
      "date": "Dec 23",
      "fulldate": "12/23/2024",
      "gamedate": "2024-12-23 00:00:00",
      "gameid": "2693940",
      "gametype": "REGULAR",
      "rotogameid": "43830",
      "opp": "@DEN",
      "oppraw": "DEN",
      "teamURL": "/basketball/team/denver-nuggets-den",
      "home": false,
      "score": "117-<span class=\"bold\">90</span>",
      "gameURL": "/basketball/box-score/nuggets-vs-suns-2024-12-23-2693940",
      "min": "7",
      "started": "",
      "pts": "0",
      "reb": "0",
      "ast": "0",
      "stl": "0",
      "blk": "0",
      "to": "0",
      "fgm": "0",
      "fga": "4",
      "ftm": "0",
      "fta": "0",
      "pt3fgm": "0",
      "pt3fga": "2",
      "oreb": "0",
      "dreb": "0",
      "fouls": "1",
      "nbafpts": ".0",
      "fgpct": 0,
      "pt3fgpct": 0,
      "ftpct": 0,
      "playedgame": "1",
      "season": "2024",
      "nbaPts": "0.0",
      "fanduelPts": "0.0",
      "draftkingsPts": "0.0",
      "yahooPts": "0.0",
      "sorarePts": "0.0",
      "fanballPts": "0.0",
      "head2headPts": "0.0",
      "dream11Pts": "0.0"
    },
    {
      "playerid": "",
      "team": "PHX",
      "date": "Dec 21",
      "fulldate": "",
      "gamedate": "2024-12-21 00:00:00",
      "gameid": "2694526",
      "gametype": "",
      "rotogameid": "",
      "opp": "DET",
      "oppraw": "DET",
      "teamURL": "",
      "home": "",
      "score": "<span class=\"bold\">125</span>-133",
      "gameURL": "/basketball/box-score/suns-vs-pistons-2024-12-21-2694526",
      "min": "DNP",
      "started": "",
      "pts": "",
      "reb": "",
      "ast": "",
      "stl": "",
      "blk": "",
      "to": "",
      "fgm": "",
      "fga": "",
      "ftm": "",
      "fta": "",
      "pt3fgm": "",
      "pt3fga": "",
      "oreb": "",
      "dreb": "",
      "fouls": "",
      "nbafpts": "",
      "fgpct": "",
      "pt3fgpct": "",
      "ftpct": "",
      "playedgame": "",
      "season": "",
      "nbaPts": "",
      "fanduelPts": "",
      "draftkingsPts": "",
      "yahooPts": "",
      "sorarePts": "",
      "fanballPts": "",
      "head2headPts": "",
      "dream11Pts": ""
    },
    {
      "playerid": "",
      "team": "PHX",
      "date": "Dec 19",
      "fulldate": "",
      "gamedate": "2024-12-19 00:00:00",
      "gameid": "2694524",
      "gametype": "",
      "rotogameid": "",
      "opp": "IND",
      "oppraw": "IND",
      "teamURL": "",
      "home": "",
      "score": "<span class=\"bold\">111</span>-120",
      "gameURL": "/basketball/box-score/suns-vs-pacers-2024-12-19-2694524",
      "min": "DNP",
      "started": "",
      "pts": "",
      "reb": "",
      "ast": "",
      "stl": "",
      "blk": "",
      "to": "",
      "fgm": "",
      "fga": "",
      "ftm": "",
      "fta": "",
      "pt3fgm": "",
      "pt3fga": "",
      "oreb": "",
      "dreb": "",
      "fouls": "",
      "nbafpts": "",
      "fgpct": "",
      "pt3fgpct": "",
      "ftpct": "",
      "playedgame": "",
      "season": "",
      "nbaPts": "",
      "fanduelPts": "",
      "draftkingsPts": "",
      "yahooPts": "",
      "sorarePts": "",
      "fanballPts": "",
      "head2headPts": "",
      "dream11Pts": ""
    },
    {
      "playerid": "",
      "team": "PHX",
      "date": "Dec 15",
      "fulldate": "",
      "gamedate": "2024-12-15 00:00:00",
      "gameid": "2716380",
      "gametype": "",
      "rotogameid": "",
      "opp": "POR",
      "oppraw": "POR",
      "teamURL": "",
      "home": "",
      "score": "<span class=\"bold\">116</span>-109",
      "gameURL": "/basketball/box-score/suns-vs-trail-blazers-2024-12-15-2716380",
      "min": "DNP",
      "started": "",
      "pts": "",
      "reb": "",
      "ast": "",
      "stl": "",
      "blk": "",
      "to": "",
      "fgm": "",
      "fga": "",
      "ftm": "",
      "fta": "",
      "pt3fgm": "",
      "pt3fga": "",
      "oreb": "",
      "dreb": "",
      "fouls": "",
      "nbafpts": "",
      "fgpct": "",
      "pt3fgpct": "",
      "ftpct": "",
      "playedgame": "",
      "season": "",
      "nbaPts": "",
      "fanduelPts": "",
      "draftkingsPts": "",
      "yahooPts": "",
      "sorarePts": "",
      "fanballPts": "",
      "head2headPts": "",
      "dream11Pts": ""
    },
    {
      "playerid": "",
      "team": "PHX",
      "date": "Dec 13",
      "fulldate": "",
      "gamedate": "2024-12-13 00:00:00",
      "gameid": "2716375",
      "gametype": "",
      "rotogameid": "",
      "opp": "@UTA",
      "oppraw": "UTA",
      "teamURL": "",
      "home": "",
      "score": "126-<span class=\"bold\">134</span>",
      "gameURL": "/basketball/box-score/jazz-vs-suns-2024-12-13-2716375",
      "min": "DNP",
      "started": "",
      "pts": "",
      "reb": "",
      "ast": "",
      "stl": "",
      "blk": "",
      "to": "",
      "fgm": "",
      "fga": "",
      "ftm": "",
      "fta": "",
      "pt3fgm": "",
      "pt3fga": "",
      "oreb": "",
      "dreb": "",
      "fouls": "",
      "nbafpts": "",
      "fgpct": "",
      "pt3fgpct": "",
      "ftpct": "",
      "playedgame": "",
      "season": "",
      "nbaPts": "",
      "fanduelPts": "",
      "draftkingsPts": "",
      "yahooPts": "",
      "sorarePts": "",
      "fanballPts": "",
      "head2headPts": "",
      "dream11Pts": ""
    },
    {
      "playerid": "",
      "team": "PHX",
      "date": "Dec 8",
      "fulldate": "",
      "gamedate": "2024-12-08 00:00:00",
      "gameid": "2694354",
      "gametype": "",
      "rotogameid": "",
      "opp": "@ORL",
      "oppraw": "ORL",
      "teamURL": "",
      "home": "",
      "score": "115-<span class=\"bold\">110</span>",
      "gameURL": "/basketball/box-score/magic-vs-suns-2024-12-08-2694354",
      "min": "DNP",
      "started": "",
      "pts": "",
      "reb": "",
      "ast": "",
      "stl": "",
      "blk": "",
      "to": "",
      "fgm": "",
      "fga": "",
      "ftm": "",
      "fta": "",
      "pt3fgm": "",
      "pt3fga": "",
      "oreb": "",
      "dreb": "",
      "fouls": "",
      "nbafpts": "",
      "fgpct": "",
      "pt3fgpct": "",
      "ftpct": "",
      "playedgame": "",
      "season": "",
      "nbaPts": "",
      "fanduelPts": "",
      "draftkingsPts": "",
      "yahooPts": "",
      "sorarePts": "",
      "fanballPts": "",
      "head2headPts": "",
      "dream11Pts": ""
    },
    {
      "playerid": "",
      "team": "PHX",
      "date": "Dec 7",
      "fulldate": "",
      "gamedate": "2024-12-07 00:00:00",
      "gameid": "2694140",
      "gametype": "",
      "rotogameid": "",
      "opp": "@MIA",
      "oppraw": "MIA",
      "teamURL": "",
      "home": "",
      "score": "121-<span class=\"bold\">111</span>",
      "gameURL": "/basketball/box-score/heat-vs-suns-2024-12-07-2694140",
      "min": "DNP",
      "started": "",
      "pts": "",
      "reb": "",
      "ast": "",
      "stl": "",
      "blk": "",
      "to": "",
      "fgm": "",
      "fga": "",
      "ftm": "",
      "fta": "",
      "pt3fgm": "",
      "pt3fga": "",
      "oreb": "",
      "dreb": "",
      "fouls": "",
      "nbafpts": "",
      "fgpct": "",
      "pt3fgpct": "",
      "ftpct": "",
      "playedgame": "",
      "season": "",
      "nbaPts": "",
      "fanduelPts": "",
      "draftkingsPts": "",
      "yahooPts": "",
      "sorarePts": "",
      "fanballPts": "",
      "head2headPts": "",
      "dream11Pts": ""
    },
    {
      "playerid": "",
      "team": "PHX",
      "date": "Dec 5",
      "fulldate": "",
      "gamedate": "2024-12-05 00:00:00",
      "gameid": "2694382",
      "gametype": "",
      "rotogameid": "",
      "opp": "@NOP",
      "oppraw": "NOP",
      "teamURL": "",
      "home": "",
      "score": "126-<span class=\"bold\">124</span>",
      "gameURL": "/basketball/box-score/pelicans-vs-suns-2024-12-05-2694382",
      "min": "DNP",
      "started": "",
      "pts": "",
      "reb": "",
      "ast": "",
      "stl": "",
      "blk": "",
      "to": "",
      "fgm": "",
      "fga": "",
      "ftm": "",
      "fta": "",
      "pt3fgm": "",
      "pt3fga": "",
      "oreb": "",
      "dreb": "",
      "fouls": "",
      "nbafpts": "",
      "fgpct": "",
      "pt3fgpct": "",
      "ftpct": "",
      "playedgame": "",
      "season": "",
      "nbaPts": "",
      "fanduelPts": "",
      "draftkingsPts": "",
      "yahooPts": "",
      "sorarePts": "",
      "fanballPts": "",
      "head2headPts": "",
      "dream11Pts": ""
    },
    {
      "playerid": "",
      "team": "PHX",
      "date": "Dec 3",
      "fulldate": "",
      "gamedate": "2024-12-03 00:00:00",
      "gameid": "2692562",
      "gametype": "",
      "rotogameid": "",
      "opp": "SAS",
      "oppraw": "SAS",
      "teamURL": "",
      "home": "",
      "score": "<span class=\"bold\">104</span>-93",
      "gameURL": "/basketball/box-score/suns-vs-spurs-2024-12-03-2692562",
      "min": "DNP",
      "started": "",
      "pts": "",
      "reb": "",
      "ast": "",
      "stl": "",
      "blk": "",
      "to": "",
      "fgm": "",
      "fga": "",
      "ftm": "",
      "fta": "",
      "pt3fgm": "",
      "pt3fga": "",
      "oreb": "",
      "dreb": "",
      "fouls": "",
      "nbafpts": "",
      "fgpct": "",
      "pt3fgpct": "",
      "ftpct": "",
      "playedgame": "",
      "season": "",
      "nbaPts": "",
      "fanduelPts": "",
      "draftkingsPts": "",
      "yahooPts": "",
      "sorarePts": "",
      "fanballPts": "",
      "head2headPts": "",
      "dream11Pts": ""
    },
    {
      "playerid": "",
      "team": "PHX",
      "date": "Nov 30",
      "fulldate": "",
      "gamedate": "2024-11-30 00:00:00",
      "gameid": "2694520",
      "gametype": "",
      "rotogameid": "",
      "opp": "GSW",
      "oppraw": "GSW",
      "teamURL": "",
      "home": "",
      "score": "<span class=\"bold\">113</span>-105",
      "gameURL": "/basketball/box-score/suns-vs-warriors-2024-11-30-2694520",
      "min": "DNP",
      "started": "",
      "pts": "",
      "reb": "",
      "ast": "",
      "stl": "",
      "blk": "",
      "to": "",
      "fgm": "",
      "fga": "",
      "ftm": "",
      "fta": "",
      "pt3fgm": "",
      "pt3fga": "",
      "oreb": "",
      "dreb": "",
      "fouls": "",
      "nbafpts": "",
      "fgpct": "",
      "pt3fgpct": "",
      "ftpct": "",
      "playedgame": "",
      "season": "",
      "nbaPts": "",
      "fanduelPts": "",
      "draftkingsPts": "",
      "yahooPts": "",
      "sorarePts": "",
      "fanballPts": "",
      "head2headPts": "",
      "dream11Pts": ""
    },
    {
      "playerid": "",
      "team": "PHX",
      "date": "Nov 27",
      "fulldate": "",
      "gamedate": "2024-11-27 00:00:00",
      "gameid": "2694515",
      "gametype": "",
      "rotogameid": "",
      "opp": "BKN",
      "oppraw": "BKN",
      "teamURL": "",
      "home": "",
      "score": "<span class=\"bold\">117</span>-127",
      "gameURL": "/basketball/box-score/suns-vs-nets-2024-11-27-2694515",
      "min": "DNP",
      "started": "",
      "pts": "",
      "reb": "",
      "ast": "",
      "stl": "",
      "blk": "",
      "to": "",
      "fgm": "",
      "fga": "",
      "ftm": "",
      "fta": "",
      "pt3fgm": "",
      "pt3fga": "",
      "oreb": "",
      "dreb": "",
      "fouls": "",
      "nbafpts": "",
      "fgpct": "",
      "pt3fgpct": "",
      "ftpct": "",
      "playedgame": "",
      "season": "",
      "nbaPts": "",
      "fanduelPts": "",
      "draftkingsPts": "",
      "yahooPts": "",
      "sorarePts": "",
      "fanballPts": "",
      "head2headPts": "",
      "dream11Pts": ""
    },
    {
      "playerid": "",
      "team": "PHX",
      "date": "Nov 26",
      "fulldate": "",
      "gamedate": "2024-11-26 00:00:00",
      "gameid": "2692544",
      "gametype": "",
      "rotogameid": "",
      "opp": "LAL",
      "oppraw": "LAL",
      "teamURL": "",
      "home": "",
      "score": "<span class=\"bold\">127</span>-100",
      "gameURL": "/basketball/box-score/suns-vs-lakers-2024-11-26-2692544",
      "min": "DNP",
      "started": "",
      "pts": "",
      "reb": "",
      "ast": "",
      "stl": "",
      "blk": "",
      "to": "",
      "fgm": "",
      "fga": "",
      "ftm": "",
      "fta": "",
      "pt3fgm": "",
      "pt3fga": "",
      "oreb": "",
      "dreb": "",
      "fouls": "",
      "nbafpts": "",
      "fgpct": "",
      "pt3fgpct": "",
      "ftpct": "",
      "playedgame": "",
      "season": "",
      "nbaPts": "",
      "fanduelPts": "",
      "draftkingsPts": "",
      "yahooPts": "",
      "sorarePts": "",
      "fanballPts": "",
      "head2headPts": "",
      "dream11Pts": ""
    },
    {
      "playerid": "3947",
      "team": "PHX",
      "date": "Nov 20",
      "fulldate": "11/20/2024",
      "gamedate": "2024-11-20 00:00:00",
      "gameid": "2694512",
      "gametype": "REGULAR",
      "rotogameid": "43701",
      "opp": "NYK",
      "oppraw": "NYK",
      "teamURL": "/basketball/team/new-york-knicks-nyk",
      "home": true,
      "score": "<span class=\"bold\">122</span>-138",
      "gameURL": "/basketball/box-score/suns-vs-knicks-2024-11-20-2694512",
      "min": "4",
      "started": "",
      "pts": "4",
      "reb": "0",
      "ast": "1",
      "stl": "1",
      "blk": "0",
      "to": "1",
      "fgm": "1",
      "fga": "5",
      "ftm": "2",
      "fta": "2",
      "pt3fgm": "0",
      "pt3fga": "4",
      "oreb": "0",
      "dreb": "0",
      "fouls": "0",
      "nbafpts": "7.5",
      "fgpct": 0.2,
      "pt3fgpct": 0,
      "ftpct": 1,
      "playedgame": "1",
      "season": "2024",
      "nbaPts": "7.5",
      "fanduelPts": "7.5",
      "draftkingsPts": "7.0",
      "yahooPts": "6.5",
      "sorarePts": "6.5",
      "fanballPts": "7.5",
      "head2headPts": "0.0",
      "dream11Pts": "7.5"
    },
    {
      "playerid": "",
      "team": "PHX",
      "date": "Nov 18",
      "fulldate": "",
      "gamedate": "2024-11-18 00:00:00",
      "gameid": "2694509",
      "gametype": "",
      "rotogameid": "",
      "opp": "ORL",
      "oppraw": "ORL",
      "teamURL": "",
      "home": "",
      "score": "<span class=\"bold\">99</span>-109",
      "gameURL": "/basketball/box-score/suns-vs-magic-2024-11-18-2694509",
      "min": "DNP",
      "started": "",
      "pts": "",
      "reb": "",
      "ast": "",
      "stl": "",
      "blk": "",
      "to": "",
      "fgm": "",
      "fga": "",
      "ftm": "",
      "fta": "",
      "pt3fgm": "",
      "pt3fga": "",
      "oreb": "",
      "dreb": "",
      "fouls": "",
      "nbafpts": "",
      "fgpct": "",
      "pt3fgpct": "",
      "ftpct": "",
      "playedgame": "",
      "season": "",
      "nbaPts": "",
      "fanduelPts": "",
      "draftkingsPts": "",
      "yahooPts": "",
      "sorarePts": "",
      "fanballPts": "",
      "head2headPts": "",
      "dream11Pts": ""
    },
    {
      "playerid": "",
      "team": "PHX",
      "date": "Nov 17",
      "fulldate": "",
      "gamedate": "2024-11-17 00:00:00",
      "gameid": "2694674",
      "gametype": "",
      "rotogameid": "",
      "opp": "@MIN",
      "oppraw": "MIN",
      "teamURL": "",
      "home": "",
      "score": "120-<span class=\"bold\">117</span>",
      "gameURL": "/basketball/box-score/timberwolves-vs-suns-2024-11-17-2694674",
      "min": "DNP",
      "started": "",
      "pts": "",
      "reb": "",
      "ast": "",
      "stl": "",
      "blk": "",
      "to": "",
      "fgm": "",
      "fga": "",
      "ftm": "",
      "fta": "",
      "pt3fgm": "",
      "pt3fga": "",
      "oreb": "",
      "dreb": "",
      "fouls": "",
      "nbafpts": "",
      "fgpct": "",
      "pt3fgpct": "",
      "ftpct": "",
      "playedgame": "",
      "season": "",
      "nbaPts": "",
      "fanduelPts": "",
      "draftkingsPts": "",
      "yahooPts": "",
      "sorarePts": "",
      "fanballPts": "",
      "head2headPts": "",
      "dream11Pts": ""
    },
    {
      "playerid": "3947",
      "team": "PHX",
      "date": "Nov 15",
      "fulldate": "11/15/2024",
      "gamedate": "2024-11-15 00:00:00",
      "gameid": "2692523",
      "gametype": "REGULAR",
      "rotogameid": "43457",
      "opp": "@OKC",
      "oppraw": "OKC",
      "teamURL": "/basketball/team/oklahoma-city-thunder-okc",
      "home": false,
      "score": "99-<span class=\"bold\">83</span>",
      "gameURL": "/basketball/box-score/thunder-vs-suns-2024-11-15-2692523",
      "min": "5",
      "started": "",
      "pts": "5",
      "reb": "2",
      "ast": "1",
      "stl": "1",
      "blk": "0",
      "to": "0",
      "fgm": "1",
      "fga": "2",
      "ftm": "2",
      "fta": "2",
      "pt3fgm": "1",
      "pt3fga": "1",
      "oreb": "0",
      "dreb": "2",
      "fouls": "0",
      "nbafpts": "11.9",
      "fgpct": 0.5,
      "pt3fgpct": 1,
      "ftpct": 1,
      "playedgame": "1",
      "season": "2024",
      "nbaPts": "11.9",
      "fanduelPts": "11.9",
      "draftkingsPts": "11.5",
      "yahooPts": "11.4",
      "sorarePts": "12.9",
      "fanballPts": "11.0",
      "head2headPts": "0.0",
      "dream11Pts": "11.9"
    },
    {
      "playerid": "3947",
      "team": "PHX",
      "date": "Nov 13",
      "fulldate": "11/13/2024",
      "gamedate": "2024-11-13 00:00:00",
      "gameid": "2694223",
      "gametype": "REGULAR",
      "rotogameid": "43675",
      "opp": "@SAC",
      "oppraw": "SAC",
      "teamURL": "/basketball/team/sacramento-kings-sac",
      "home": false,
      "score": "127-<span class=\"bold\">104</span>",
      "gameURL": "/basketball/box-score/kings-vs-suns-2024-11-13-2694223",
      "min": "11",
      "started": "",
      "pts": "4",
      "reb": "0",
      "ast": "1",
      "stl": "0",
      "blk": "0",
      "to": "1",
      "fgm": "1",
      "fga": "4",
      "ftm": "2",
      "fta": "2",
      "pt3fgm": "0",
      "pt3fga": "2",
      "oreb": "0",
      "dreb": "0",
      "fouls": "0",
      "nbafpts": "4.5",
      "fgpct": 0.25,
      "pt3fgpct": 0,
      "ftpct": 1,
      "playedgame": "1",
      "season": "2024",
      "nbaPts": "4.5",
      "fanduelPts": "4.5",
      "draftkingsPts": "5.0",
      "yahooPts": "4.5",
      "sorarePts": "3.5",
      "fanballPts": "5.5",
      "head2headPts": "0.0",
      "dream11Pts": "4.5"
    },
    {
      "playerid": "",
      "team": "PHX",
      "date": "Nov 12",
      "fulldate": "",
      "gamedate": "2024-11-12 00:00:00",
      "gameid": "2692511",
      "gametype": "",
      "rotogameid": "",
      "opp": "@UTA",
      "oppraw": "UTA",
      "teamURL": "",
      "home": "",
      "score": "112-<span class=\"bold\">120</span>",
      "gameURL": "/basketball/box-score/jazz-vs-suns-2024-11-12-2692511",
      "min": "DNP",
      "started": "",
      "pts": "",
      "reb": "",
      "ast": "",
      "stl": "",
      "blk": "",
      "to": "",
      "fgm": "",
      "fga": "",
      "ftm": "",
      "fta": "",
      "pt3fgm": "",
      "pt3fga": "",
      "oreb": "",
      "dreb": "",
      "fouls": "",
      "nbafpts": "",
      "fgpct": "",
      "pt3fgpct": "",
      "ftpct": "",
      "playedgame": "",
      "season": "",
      "nbaPts": "",
      "fanduelPts": "",
      "draftkingsPts": "",
      "yahooPts": "",
      "sorarePts": "",
      "fanballPts": "",
      "head2headPts": "",
      "dream11Pts": ""
    },
    {
      "playerid": "",
      "team": "PHX",
      "date": "Nov 10",
      "fulldate": "",
      "gamedate": "2024-11-10 00:00:00",
      "gameid": "2694507",
      "gametype": "",
      "rotogameid": "",
      "opp": "SAC",
      "oppraw": "SAC",
      "teamURL": "",
      "home": "",
      "score": "<span class=\"bold\">118</span>-127",
      "gameURL": "/basketball/box-score/suns-vs-kings-2024-11-10-2694507",
      "min": "DNP",
      "started": "",
      "pts": "",
      "reb": "",
      "ast": "",
      "stl": "",
      "blk": "",
      "to": "",
      "fgm": "",
      "fga": "",
      "ftm": "",
      "fta": "",
      "pt3fgm": "",
      "pt3fga": "",
      "oreb": "",
      "dreb": "",
      "fouls": "",
      "nbafpts": "",
      "fgpct": "",
      "pt3fgpct": "",
      "ftpct": "",
      "playedgame": "",
      "season": "",
      "nbaPts": "",
      "fanduelPts": "",
      "draftkingsPts": "",
      "yahooPts": "",
      "sorarePts": "",
      "fanballPts": "",
      "head2headPts": "",
      "dream11Pts": ""
    },
    {
      "playerid": "",
      "team": "PHX",
      "date": "Nov 8",
      "fulldate": "",
      "gamedate": "2024-11-08 00:00:00",
      "gameid": "2693876",
      "gametype": "",
      "rotogameid": "",
      "opp": "@DAL",
      "oppraw": "DAL",
      "teamURL": "",
      "home": "",
      "score": "113-<span class=\"bold\">114</span>",
      "gameURL": "/basketball/box-score/mavericks-vs-suns-2024-11-08-2693876",
      "min": "DNP",
      "started": "",
      "pts": "",
      "reb": "",
      "ast": "",
      "stl": "",
      "blk": "",
      "to": "",
      "fgm": "",
      "fga": "",
      "ftm": "",
      "fta": "",
      "pt3fgm": "",
      "pt3fga": "",
      "oreb": "",
      "dreb": "",
      "fouls": "",
      "nbafpts": "",
      "fgpct": "",
      "pt3fgpct": "",
      "ftpct": "",
      "playedgame": "",
      "season": "",
      "nbaPts": "",
      "fanduelPts": "",
      "draftkingsPts": "",
      "yahooPts": "",
      "sorarePts": "",
      "fanballPts": "",
      "head2headPts": "",
      "dream11Pts": ""
    },
    {
      "playerid": "",
      "team": "PHX",
      "date": "Nov 6",
      "fulldate": "",
      "gamedate": "2024-11-06 00:00:00",
      "gameid": "2694503",
      "gametype": "",
      "rotogameid": "",
      "opp": "MIA",
      "oppraw": "MIA",
      "teamURL": "",
      "home": "",
      "score": "<span class=\"bold\">115</span>-112",
      "gameURL": "/basketball/box-score/suns-vs-heat-2024-11-06-2694503",
      "min": "DNP",
      "started": "",
      "pts": "",
      "reb": "",
      "ast": "",
      "stl": "",
      "blk": "",
      "to": "",
      "fgm": "",
      "fga": "",
      "ftm": "",
      "fta": "",
      "pt3fgm": "",
      "pt3fga": "",
      "oreb": "",
      "dreb": "",
      "fouls": "",
      "nbafpts": "",
      "fgpct": "",
      "pt3fgpct": "",
      "ftpct": "",
      "playedgame": "",
      "season": "",
      "nbaPts": "",
      "fanduelPts": "",
      "draftkingsPts": "",
      "yahooPts": "",
      "sorarePts": "",
      "fanballPts": "",
      "head2headPts": "",
      "dream11Pts": ""
    },
    {
      "playerid": "",
      "team": "PHX",
      "date": "Nov 4",
      "fulldate": "",
      "gamedate": "2024-11-04 00:00:00",
      "gameid": "2694500",
      "gametype": "",
      "rotogameid": "",
      "opp": "PHI",
      "oppraw": "PHI",
      "teamURL": "",
      "home": "",
      "score": "<span class=\"bold\">118</span>-116",
      "gameURL": "/basketball/box-score/suns-vs-76ers-2024-11-04-2694500",
      "min": "DNP",
      "started": "",
      "pts": "",
      "reb": "",
      "ast": "",
      "stl": "",
      "blk": "",
      "to": "",
      "fgm": "",
      "fga": "",
      "ftm": "",
      "fta": "",
      "pt3fgm": "",
      "pt3fga": "",
      "oreb": "",
      "dreb": "",
      "fouls": "",
      "nbafpts": "",
      "fgpct": "",
      "pt3fgpct": "",
      "ftpct": "",
      "playedgame": "",
      "season": "",
      "nbaPts": "",
      "fanduelPts": "",
      "draftkingsPts": "",
      "yahooPts": "",
      "sorarePts": "",
      "fanballPts": "",
      "head2headPts": "",
      "dream11Pts": ""
    },
    {
      "playerid": "",
      "team": "PHX",
      "date": "Nov 2",
      "fulldate": "",
      "gamedate": "2024-11-02 00:00:00",
      "gameid": "2694494",
      "gametype": "",
      "rotogameid": "",
      "opp": "POR",
      "oppraw": "POR",
      "teamURL": "",
      "home": "",
      "score": "<span class=\"bold\">103</span>-97",
      "gameURL": "/basketball/box-score/suns-vs-trail-blazers-2024-11-02-2694494",
      "min": "DNP",
      "started": "",
      "pts": "",
      "reb": "",
      "ast": "",
      "stl": "",
      "blk": "",
      "to": "",
      "fgm": "",
      "fga": "",
      "ftm": "",
      "fta": "",
      "pt3fgm": "",
      "pt3fga": "",
      "oreb": "",
      "dreb": "",
      "fouls": "",
      "nbafpts": "",
      "fgpct": "",
      "pt3fgpct": "",
      "ftpct": "",
      "playedgame": "",
      "season": "",
      "nbaPts": "",
      "fanduelPts": "",
      "draftkingsPts": "",
      "yahooPts": "",
      "sorarePts": "",
      "fanballPts": "",
      "head2headPts": "",
      "dream11Pts": ""
    },
    {
      "playerid": "",
      "team": "PHX",
      "date": "Oct 31",
      "fulldate": "",
      "gamedate": "2024-10-31 00:00:00",
      "gameid": "2694313",
      "gametype": "",
      "rotogameid": "",
      "opp": "@LAC",
      "oppraw": "LAC",
      "teamURL": "",
      "home": "",
      "score": "119-<span class=\"bold\">125</span>",
      "gameURL": "/basketball/box-score/clippers-vs-suns-2024-10-31-2694313",
      "min": "DNP",
      "started": "",
      "pts": "",
      "reb": "",
      "ast": "",
      "stl": "",
      "blk": "",
      "to": "",
      "fgm": "",
      "fga": "",
      "ftm": "",
      "fta": "",
      "pt3fgm": "",
      "pt3fga": "",
      "oreb": "",
      "dreb": "",
      "fouls": "",
      "nbafpts": "",
      "fgpct": "",
      "pt3fgpct": "",
      "ftpct": "",
      "playedgame": "",
      "season": "",
      "nbaPts": "",
      "fanduelPts": "",
      "draftkingsPts": "",
      "yahooPts": "",
      "sorarePts": "",
      "fanballPts": "",
      "head2headPts": "",
      "dream11Pts": ""
    },
    {
      "playerid": "",
      "team": "PHX",
      "date": "Oct 28",
      "fulldate": "",
      "gamedate": "2024-10-28 00:00:00",
      "gameid": "2694491",
      "gametype": "",
      "rotogameid": "",
      "opp": "LAL",
      "oppraw": "LAL",
      "teamURL": "",
      "home": "",
      "score": "<span class=\"bold\">109</span>-105",
      "gameURL": "/basketball/box-score/suns-vs-lakers-2024-10-28-2694491",
      "min": "DNP",
      "started": "",
      "pts": "",
      "reb": "",
      "ast": "",
      "stl": "",
      "blk": "",
      "to": "",
      "fgm": "",
      "fga": "",
      "ftm": "",
      "fta": "",
      "pt3fgm": "",
      "pt3fga": "",
      "oreb": "",
      "dreb": "",
      "fouls": "",
      "nbafpts": "",
      "fgpct": "",
      "pt3fgpct": "",
      "ftpct": "",
      "playedgame": "",
      "season": "",
      "nbaPts": "",
      "fanduelPts": "",
      "draftkingsPts": "",
      "yahooPts": "",
      "sorarePts": "",
      "fanballPts": "",
      "head2headPts": "",
      "dream11Pts": ""
    },
    {
      "playerid": "3947",
      "team": "PHX",
      "date": "Oct 26",
      "fulldate": "10/26/2024",
      "gamedate": "2024-10-26 00:00:00",
      "gameid": "2694487",
      "gametype": "REGULAR",
      "rotogameid": "43558",
      "opp": "DAL",
      "oppraw": "DAL",
      "teamURL": "/basketball/team/dallas-mavericks-dal",
      "home": true,
      "score": "<span class=\"bold\">114</span>-102",
      "gameURL": "/basketball/box-score/suns-vs-mavericks-2024-10-26-2694487",
      "min": "18",
      "started": "",
      "pts": "2",
      "reb": "3",
      "ast": "2",
      "stl": "0",
      "blk": "0",
      "to": "1",
      "fgm": "1",
      "fga": "3",
      "ftm": "0",
      "fta": "0",
      "pt3fgm": "0",
      "pt3fga": "2",
      "oreb": "0",
      "dreb": "3",
      "fouls": "1",
      "nbafpts": "7.6",
      "fgpct": 0.3333333333333333,
      "pt3fgpct": 0,
      "ftpct": 0,
      "playedgame": "1",
      "season": "2024",
      "nbaPts": "7.6",
      "fanduelPts": "7.6",
      "draftkingsPts": "8.3",
      "yahooPts": "7.6",
      "sorarePts": "6.6",
      "fanballPts": "8.8",
      "head2headPts": "0.0",
      "dream11Pts": "7.6"
    },
    {
      "playerid": "",
      "team": "PHX",
      "date": "Oct 25",
      "fulldate": "",
      "gamedate": "2024-10-25 00:00:00",
      "gameid": "2694419",
      "gametype": "",
      "rotogameid": "",
      "opp": "@LAL",
      "oppraw": "LAL",
      "teamURL": "",
      "home": "",
      "score": "123-<span class=\"bold\">116</span>",
      "gameURL": "/basketball/box-score/lakers-vs-suns-2024-10-25-2694419",
      "min": "DNP",
      "started": "",
      "pts": "",
      "reb": "",
      "ast": "",
      "stl": "",
      "blk": "",
      "to": "",
      "fgm": "",
      "fga": "",
      "ftm": "",
      "fta": "",
      "pt3fgm": "",
      "pt3fga": "",
      "oreb": "",
      "dreb": "",
      "fouls": "",
      "nbafpts": "",
      "fgpct": "",
      "pt3fgpct": "",
      "ftpct": "",
      "playedgame": "",
      "season": "",
      "nbaPts": "",
      "fanduelPts": "",
      "draftkingsPts": "",
      "yahooPts": "",
      "sorarePts": "",
      "fanballPts": "",
      "head2headPts": "",
      "dream11Pts": ""
    },
    {
      "playerid": "",
      "team": "PHX",
      "date": "Oct 23",
      "fulldate": "",
      "gamedate": "2024-10-23 00:00:00",
      "gameid": "2694311",
      "gametype": "",
      "rotogameid": "",
      "opp": "@LAC",
      "oppraw": "LAC",
      "teamURL": "",
      "home": "",
      "score": "113-<span class=\"bold\">116</span>",
      "gameURL": "/basketball/box-score/clippers-vs-suns-2024-10-23-2694311",
      "min": "DNP",
      "started": "",
      "pts": "",
      "reb": "",
      "ast": "",
      "stl": "",
      "blk": "",
      "to": "",
      "fgm": "",
      "fga": "",
      "ftm": "",
      "fta": "",
      "pt3fgm": "",
      "pt3fga": "",
      "oreb": "",
      "dreb": "",
      "fouls": "",
      "nbafpts": "",
      "fgpct": "",
      "pt3fgpct": "",
      "ftpct": "",
      "playedgame": "",
      "season": "",
      "nbaPts": "",
      "fanduelPts": "",
      "draftkingsPts": "",
      "yahooPts": "",
      "sorarePts": "",
      "fanballPts": "",
      "head2headPts": "",
      "dream11Pts": ""
    }
  ],
  "splits": {
    "home": {
      "season": "Home",
      "games": "4",
      "minutes": "6.3",
      "pts": "2.0",
      "reb": "0.8",
      "ast": "0.8",
      "stl": "0.3",
      "blk": "0.0",
      "pt3m": "0.0",
      "fgpct": "27.3",
      "ftpct": "100.0",
      "to": "0.5",
      "oreb": "0.0",
      "dreb": "0.8",
      "pt3a": "1.8",
      "pt3pct": "0.0",
      "fgm": "0.8",
      "fga": "2.8",
      "ftm": "0.5",
      "fta": "0.5"
    },
    "away": {
      "season": "Away",
      "games": "4",
      "minutes": "6.0",
      "pts": "2.8",
      "reb": "0.8",
      "ast": "0.5",
      "stl": "0.3",
      "blk": "0.0",
      "pt3m": "0.3",
      "fgpct": "20.0",
      "ftpct": "100.0",
      "to": "0.3",
      "oreb": "0.3",
      "dreb": "0.5",
      "pt3a": "1.3",
      "pt3pct": "20.0",
      "fgm": "0.5",
      "fga": "2.5",
      "ftm": "1.5",
      "fta": "1.5"
    }
  },
  "news": [
    {
      "headline": "",
      "date": "December 31, 2024",
      "news": "Lee produced zero points (0-1 FG, 0-1 3Pt) across two minutes during Tuesday's 117-112 loss to the Grizzlies.",
      "analysis": "Lee cracked the rotation for just the seventh time this season, bringing his total minutes played to 48. Even with a handful of injuries, the Suns have opted to go in another direction most nights, leaving Lee as nothing more than an emergency depth piece."
    },
    {
      "headline": "Probable for Wednesday",
      "date": "October 23, 2024",
      "news": "Lee (hamstring) is available for Wednesday's season opener versus the Clippers, <a href=\"https://x.com/Amanda_Pflugrad/status/1849247929560932432\">Amanda Pflugrad of 3TV Phoenix</a> reports.",
      "analysis": "<a href=\"/subscribe/\">Subscribe now</a> to instantly reveal our take on this news."
    },
    {
      "headline": "Nursing hamstring injury",
      "date": "October 22, 2024",
      "news": "Lee (hamstring) is probable for Wednesday's regular-season opener against the Clippers, <a href=\"https://x.com/GeraldBourguet/status/1848822462923821351\">Gerald Bourguet of GoPHNX.com</a> reports.",
      "analysis": "<a href=\"/subscribe/\">Subscribe now</a> to instantly reveal our take on this news."
    },
    {
      "headline": "Plays six minutes off bench Friday",
      "date": "October 21, 2024",
      "news": "Head coach Mike Budenholzer said Monday that Lee is dealing with a hamstring issue but is close to returning, <a href=\"https://x.com/GeraldBourguet/status/1848473533829005563\">Gerald Bourguet of GoPHNX.com</a> reports.",
      "analysis": "<a href=\"/subscribe/\">Subscribe now</a> to instantly reveal our take on this news."
    },
    {
      "headline": "Headed to locker room",
      "date": "October 11, 2024",
      "news": "Lee (groin) played six minutes off the bench in Friday's 109-91 preseason loss to the Pistons. He finished scoreless (0-4 FG, 0-2 3Pt).",
      "analysis": "<a href=\"/subscribe/\">Subscribe now</a> to instantly reveal our take on this news."
    },
    {
      "headline": "",
      "date": "October 8, 2024",
      "news": "Lee went to the locker room with 8:49 remaining in the fourth quarter of Tuesday's preseason game against the Pistons after taking a hit to the groin/leg area, <a href=\"https://x.com/GeraldBourguet/status/1843818638291415385\">Gerald Bourguet of GoPHNX.com</a> reports.",
      "analysis": "<a href=\"/subscribe/\">Subscribe now</a> to instantly reveal our take on this news."
    }
  ]
}